{
  "job_id": "img20260331152449",
  "status": "succeeded",
  "input": {
    "filename": "original.jpg",
    "content_type": "image/jpeg",
    "size_bytes": 3614304,
    "width": 3000,
    "height": 4000,
    "preprocess_metrics": {
      "width": 3000,
      "height": 4000,
      "brightness": 172.40329925,
      "contrast": 44.64580625842644,
      "skew_angle_deg": 0.0,
      "perspective_score": 0.6975907227879131
    }
  },
  "warnings": [
    "homr wrote MusicXML outside the dedicated OMR output directory; artifact was normalized.",
    "omr mode selected: original",
    "omr mode scores: original=6.50, enhanced=6.50, binary=5.50"
  ],
  "confidence": 0.95,
  "artifacts": [
    {
      "name": "original",
      "kind": "original",
      "path": "samples/cases/img20260331152449/original.jpg",
      "content_type": "image/jpeg",
      "size_bytes": 3614304,
      "url": null
    },
    {
      "name": "preprocessed",
      "kind": "preprocessed",
      "path": "samples/cases/img20260331152449/preprocess/preprocessed.png",
      "content_type": "image/png",
      "size_bytes": 2978551,
      "url": null
    },
    {
      "name": "preview",
      "kind": "preview",
      "path": "samples/cases/img20260331152449/preprocess/preview.png",
      "content_type": "image/png",
      "size_bytes": 466448,
      "url": null
    },
    {
      "name": "binary-input",
      "kind": "debug",
      "path": "samples/cases/img20260331152449/preprocess/binary_input.png",
      "content_type": "image/png",
      "size_bytes": 295793,
      "url": null
    },
    {
      "name": "musicxml",
      "kind": "musicxml",
      "path": "/app/samples/cases/img20260331152449/omr/result.musicxml",
      "content_type": "application/octet-stream",
      "size_bytes": 25032,
      "url": null
    },
    {
      "name": "original_teaser.png",
      "kind": "debug",
      "path": "/app/samples/cases/img20260331152449/omr/original/original_teaser.png",
      "content_type": "image/png",
      "size_bytes": 5508117,
      "url": null
    },
    {
      "name": "audio-raw",
      "kind": "audio",
      "path": "samples/cases/img20260331152449/audio/melody-120bpm-raw.wav",
      "content_type": "audio/x-wav",
      "size_bytes": 2822444,
      "url": null
    },
    {
      "name": "audio-quantized",
      "kind": "audio",
      "path": "samples/cases/img20260331152449/audio/melody-120bpm-quantized.wav",
      "content_type": "audio/x-wav",
      "size_bytes": 2822444,
      "url": null
    }
  ],
  "score": {
    "format": "musicxml",
    "musicxml_artifact_url": null,
    "measures": 18,
    "parts": 1,
    "time_signature": "4/4",
    "key_signature": "2"
  },
  "melody": {
    "notes": [
      {
        "start_beat": 0.0,
        "measure": 1,
        "beat": 3.5,
        "duration_beats": 0.5,
        "pitch": {
          "step": "A",
          "alter": 0,
          "octave": 3,
          "midi": 57
        },
        "tie": null,
        "accidental": null,
        "source_staff": 0,
        "confidence": 0.75
      },
      {
        "start_beat": 0.5,
        "measure": 1,
        "beat": 4.0,
        "duration_beats": 0.5,
        "pitch": {
          "step": "B",
          "alter": 0,
          "octave": 3,
          "midi": 59
        },
        "tie": null,
        "accidental": null,
        "source_staff": 0,
        "confidence": 0.75
      },
      {
        "start_beat": 1.0,
        "measure": 1,
        "beat": 4.5,
        "duration_beats": 0.5,
        "pitch": {
          "step": "D",
          "alter": 0,
          "octave": 4,
          "midi": 62
        },
        "tie": null,
        "accidental": null,
        "source_staff": 0,
        "confidence": 0.75
      },
      {
        "start_beat": 1.5,
        "measure": 2,
        "beat": 1.0,
        "duration_beats": 1.5,
        "pitch": {
          "step": "G",
          "alter": 0,
          "octave": 4,
          "midi": 67
        },
        "tie": null,
        "accidental": null,
        "source_staff": 0,
        "confidence": 0.75
      },
      {
        "start_beat": 3.0,
        "measure": 2,
        "beat": 2.5,
        "duration_beats": 0.5,
        "pitch": {
          "step": "G",
          "alter": 0,
          "octave": 4,
          "midi": 67
        },
        "tie": null,
        "accidental": null,
        "source_staff": 0,
        "confidence": 0.75
      },
      {
        "start_beat": 3.5,
        "measure": 2,
        "beat": 3.0,
        "duration_beats": 0.5,
        "pitch": {
          "step": "F",
          "alter": 1,
          "octave": 4,
          "midi": 66
        },
        "tie": null,
        "accidental": "sharp",
        "source_staff": 0,
        "confidence": 0.75
      },
      {
        "start_beat": 4.0,
        "measure": 2,
        "beat": 3.5,
        "duration_beats": 0.5,
        "pitch": {
          "step": "E",
          "alter": 0,
          "octave": 4,
          "midi": 64
        },
        "tie": null,
        "accidental": null,
        "source_staff": 0,
        "confidence": 0.75
      },
      {
        "start_beat": 4.5,
        "measure": 2,
        "beat": 4.0,
        "duration_beats": 0.5,
        "pitch": {
          "step": "D",
          "alter": 0,
          "octave": 4,
          "midi": 62
        },
        "tie": null,
        "accidental": null,
        "source_staff": 0,
        "confidence": 0.75
      },
      {
        "start_beat": 5.0,
        "measure": 2,
        "beat": 4.5,
        "duration_beats": 0.5,
        "pitch": {
          "step": "E",
          "alter": 0,
          "octave": 4,
          "midi": 64
        },
        "tie": null,
        "accidental": null,
        "source_staff": 0,
        "confidence": 0.75
      },
      {
        "start_beat": 5.5,
        "measure": 3,
        "beat": 1.0,
        "duration_beats": 1.0,
        "pitch": {
          "step": "F",
          "alter": 1,
          "octave": 4,
          "midi": 66
        },
        "tie": null,
        "accidental": "sharp",
        "source_staff": 0,
        "confidence": 0.75
      },
      {
        "start_beat": 6.5,
        "measure": 3,
        "beat": 2.0,
        "duration_beats": 1.0,
        "pitch": {
          "step": "F",
          "alter": 1,
          "octave": 4,
          "midi": 66
        },
        "tie": null,
        "accidental": "sharp",
        "source_staff": 0,
        "confidence": 0.75
      },
      {
        "start_beat": 8.0,
        "measure": 3,
        "beat": 3.5,
        "duration_beats": 0.5,
        "pitch": {
          "step": "A",
          "alter": 0,
          "octave": 3,
          "midi": 57
        },
        "tie": null,
        "accidental": null,
        "source_staff": 0,
        "confidence": 0.75
      },
      {
        "start_beat": 8.5,
        "measure": 3,
        "beat": 4.0,
        "duration_beats": 0.5,
        "pitch": {
          "step": "B",
          "alter": 0,
          "octave": 3,
          "midi": 59
        },
        "tie": null,
        "accidental": null,
        "source_staff": 0,
        "confidence": 0.75
      },
      {
        "start_beat": 9.0,
        "measure": 3,
        "beat": 4.5,
        "duration_beats": 0.5,
        "pitch": {
          "step": "D",
          "alter": 0,
          "octave": 4,
          "midi": 62
        },
        "tie": null,
        "accidental": null,
        "source_staff": 0,
        "confidence": 0.75
      },
      {
        "start_beat": 9.5,
        "measure": 4,
        "beat": 1.0,
        "duration_beats": 1.5,
        "pitch": {
          "step": "B",
          "alter": 0,
          "octave": 4,
          "midi": 71
        },
        "tie": null,
        "accidental": null,
        "source_staff": 0,
        "confidence": 0.75
      },
      {
        "start_beat": 11.0,
        "measure": 4,
        "beat": 2.5,
        "duration_beats": 0.5,
        "pitch": {
          "step": "B",
          "alter": 0,
          "octave": 4,
          "midi": 71
        },
        "tie": null,
        "accidental": null,
        "source_staff": 0,
        "confidence": 0.75
      },
      {
        "start_beat": 11.5,
        "measure": 4,
        "beat": 3.0,
        "duration_beats": 0.5,
        "pitch": {
          "step": "A",
          "alter": 0,
          "octave": 4,
          "midi": 69
        },
        "tie": null,
        "accidental": null,
        "source_staff": 0,
        "confidence": 0.75
      },
      {
        "start_beat": 12.0,
        "measure": 4,
        "beat": 3.5,
        "duration_beats": 0.5,
        "pitch": {
          "step": "G",
          "alter": 0,
          "octave": 4,
          "midi": 67
        },
        "tie": null,
        "accidental": null,
        "source_staff": 0,
        "confidence": 0.75
      },
      {
        "start_beat": 12.5,
        "measure": 4,
        "beat": 4.0,
        "duration_beats": 0.5,
        "pitch": {
          "step": "F",
          "alter": 1,
          "octave": 4,
          "midi": 66
        },
        "tie": null,
        "accidental": "sharp",
        "source_staff": 0,
        "confidence": 0.75
      },
      {
        "start_beat": 13.0,
        "measure": 4,
        "beat": 4.5,
        "duration_beats": 0.5,
        "pitch": {
          "step": "E",
          "alter": 0,
          "octave": 4,
          "midi": 64
        },
        "tie": null,
        "accidental": null,
        "source_staff": 0,
        "confidence": 0.75
      },
      {
        "start_beat": 13.5,
        "measure": 5,
        "beat": 1.0,
        "duration_beats": 2.0,
        "pitch": {
          "step": "A",
          "alter": 0,
          "octave": 4,
          "midi": 69
        },
        "tie": null,
        "accidental": null,
        "source_staff": 0,
        "confidence": 0.75
      },
      {
        "start_beat": 16.0,
        "measure": 5,
        "beat": 3.5,
        "duration_beats": 0.5,
        "pitch": {
          "step": "A",
          "alter": 0,
          "octave": 4,
          "midi": 69
        },
        "tie": null,
        "accidental": null,
        "source_staff": 0,
        "confidence": 0.75
      },
      {
        "start_beat": 16.5,
        "measure": 5,
        "beat": 4.0,
        "duration_beats": 0.5,
        "pitch": {
          "step": "B",
          "alter": 0,
          "octave": 4,
          "midi": 71
        },
        "tie": null,
        "accidental": null,
        "source_staff": 0,
        "confidence": 0.75
      },
      {
        "start_beat": 17.0,
        "measure": 5,
        "beat": 4.5,
        "duration_beats": 0.5,
        "pitch": {
          "step": "D",
          "alter": 0,
          "octave": 5,
          "midi": 74
        },
        "tie": null,
        "accidental": null,
        "source_staff": 0,
        "confidence": 0.75
      },
      {
        "start_beat": 17.5,
        "measure": 6,
        "beat": 1.0,
        "duration_beats": 1.5,
        "pitch": {
          "step": "G",
          "alter": 0,
          "octave": 4,
          "midi": 67
        },
        "tie": null,
        "accidental": null,
        "source_staff": 0,
        "confidence": 0.75
      },
      {
        "start_beat": 19.0,
        "measure": 6,
        "beat": 2.5,
        "duration_beats": 0.5,
        "pitch": {
          "step": "G",
          "alter": 0,
          "octave": 4,
          "midi": 67
        },
        "tie": null,
        "accidental": null,
        "source_staff": 0,
        "confidence": 0.75
      },
      {
        "start_beat": 19.5,
        "measure": 6,
        "beat": 3.0,
        "duration_beats": 0.5,
        "pitch": {
          "step": "F",
          "alter": 1,
          "octave": 4,
          "midi": 66
        },
        "tie": null,
        "accidental": "sharp",
        "source_staff": 0,
        "confidence": 0.75
      },
      {
        "start_beat": 20.0,
        "measure": 6,
        "beat": 3.5,
        "duration_beats": 0.5,
        "pitch": {
          "step": "E",
          "alter": 0,
          "octave": 4,
          "midi": 64
        },
        "tie": null,
        "accidental": null,
        "source_staff": 0,
        "confidence": 0.75
      },
      {
        "start_beat": 20.5,
        "measure": 6,
        "beat": 4.0,
        "duration_beats": 0.5,
        "pitch": {
          "step": "D",
          "alter": 1,
          "octave": 4,
          "midi": 63
        },
        "tie": null,
        "accidental": "sharp",
        "source_staff": 0,
        "confidence": 0.75
      },
      {
        "start_beat": 21.0,
        "measure": 6,
        "beat": 4.5,
        "duration_beats": 0.5,
        "pitch": {
          "step": "E",
          "alter": 0,
          "octave": 4,
          "midi": 64
        },
        "tie": null,
        "accidental": null,
        "source_staff": 0,
        "confidence": 0.75
      },
      {
        "start_beat": 21.5,
        "measure": 7,
        "beat": 1.0,
        "duration_beats": 1.0,
        "pitch": {
          "step": "A",
          "alter": 0,
          "octave": 4,
          "midi": 69
        },
        "tie": null,
        "accidental": null,
        "source_staff": 0,
        "confidence": 0.75
      },
      {
        "start_beat": 22.5,
        "measure": 7,
        "beat": 2.0,
        "duration_beats": 1.0,
        "pitch": {
          "step": "D",
          "alter": 0,
          "octave": 4,
          "midi": 62
        },
        "tie": null,
        "accidental": null,
        "source_staff": 0,
        "confidence": 0.75
      },
      {
        "start_beat": 24.0,
        "measure": 8,
        "beat": 3.5,
        "duration_beats": 0.5,
        "pitch": {
          "step": "D",
          "alter": 0,
          "octave": 4,
          "midi": 62
        },
        "tie": null,
        "accidental": null,
        "source_staff": 0,
        "confidence": 0.75
      },
      {
        "start_beat": 24.5,
        "measure": 8,
        "beat": 4.0,
        "duration_beats": 0.5,
        "pitch": {
          "step": "E",
          "alter": 0,
          "octave": 4,
          "midi": 64
        },
        "tie": null,
        "accidental": null,
        "source_staff": 0,
        "confidence": 0.75
      },
      {
        "start_beat": 25.0,
        "measure": 8,
        "beat": 4.5,
        "duration_beats": 0.5,
        "pitch": {
          "step": "F",
          "alter": 1,
          "octave": 4,
          "midi": 66
        },
        "tie": null,
        "accidental": "sharp",
        "source_staff": 0,
        "confidence": 0.75
      },
      {
        "start_beat": 25.5,
        "measure": 9,
        "beat": 1.0,
        "duration_beats": 1.5,
        "pitch": {
          "step": "B",
          "alter": 0,
          "octave": 4,
          "midi": 71
        },
        "tie": null,
        "accidental": null,
        "source_staff": 0,
        "confidence": 0.75
      },
      {
        "start_beat": 27.0,
        "measure": 9,
        "beat": 2.5,
        "duration_beats": 0.5,
        "pitch": {
          "step": "F",
          "alter": 1,
          "octave": 4,
          "midi": 66
        },
        "tie": null,
        "accidental": "sharp",
        "source_staff": 0,
        "confidence": 0.75
      },
      {
        "start_beat": 27.5,
        "measure": 9,
        "beat": 3.0,
        "duration_beats": 0.5,
        "pitch": {
          "step": "B",
          "alter": 0,
          "octave": 4,
          "midi": 71
        },
        "tie": null,
        "accidental": null,
        "source_staff": 0,
        "confidence": 0.75
      },
      {
        "start_beat": 28.0,
        "measure": 9,
        "beat": 3.5,
        "duration_beats": 0.5,
        "pitch": {
          "step": "F",
          "alter": 1,
          "octave": 4,
          "midi": 66
        },
        "tie": null,
        "accidental": "sharp",
        "source_staff": 0,
        "confidence": 0.75
      },
      {
        "start_beat": 28.5,
        "measure": 9,
        "beat": 4.0,
        "duration_beats": 0.5,
        "pitch": {
          "step": "E",
          "alter": 0,
          "octave": 4,
          "midi": 64
        },
        "tie": null,
        "accidental": null,
        "source_staff": 0,
        "confidence": 0.75
      },
      {
        "start_beat": 29.0,
        "measure": 9,
        "beat": 4.5,
        "duration_beats": 0.5,
        "pitch": {
          "step": "D",
          "alter": 0,
          "octave": 4,
          "midi": 62
        },
        "tie": null,
        "accidental": null,
        "source_staff": 0,
        "confidence": 0.75
      },
      {
        "start_beat": 29.5,
        "measure": 10,
        "beat": 1.0,
        "duration_beats": 2.0,
        "pitch": {
          "step": "E",
          "alter": 0,
          "octave": 4,
          "midi": 64
        },
        "tie": null,
        "accidental": null,
        "source_staff": 0,
        "confidence": 0.75
      },
      {
        "start_beat": 32.0,
        "measure": 10,
        "beat": 3.5,
        "duration_beats": 0.5,
        "pitch": {
          "step": "A",
          "alter": 0,
          "octave": 3,
          "midi": 57
        },
        "tie": null,
        "accidental": null,
        "source_staff": 0,
        "confidence": 0.75
      },
      {
        "start_beat": 32.5,
        "measure": 10,
        "beat": 4.0,
        "duration_beats": 0.5,
        "pitch": {
          "step": "B",
          "alter": 0,
          "octave": 3,
          "midi": 59
        },
        "tie": null,
        "accidental": null,
        "source_staff": 0,
        "confidence": 0.75
      },
      {
        "start_beat": 33.0,
        "measure": 10,
        "beat": 4.5,
        "duration_beats": 0.5,
        "pitch": {
          "step": "D",
          "alter": 0,
          "octave": 4,
          "midi": 62
        },
        "tie": null,
        "accidental": null,
        "source_staff": 0,
        "confidence": 0.75
      },
      {
        "start_beat": 33.5,
        "measure": 11,
        "beat": 1.0,
        "duration_beats": 1.5,
        "pitch": {
          "step": "G",
          "alter": 0,
          "octave": 4,
          "midi": 67
        },
        "tie": null,
        "accidental": null,
        "source_staff": 0,
        "confidence": 0.75
      },
      {
        "start_beat": 35.0,
        "measure": 11,
        "beat": 2.5,
        "duration_beats": 0.5,
        "pitch": {
          "step": "G",
          "alter": 0,
          "octave": 4,
          "midi": 67
        },
        "tie": null,
        "accidental": null,
        "source_staff": 0,
        "confidence": 0.75
      },
      {
        "start_beat": 35.5,
        "measure": 11,
        "beat": 3.0,
        "duration_beats": 0.5,
        "pitch": {
          "step": "F",
          "alter": 1,
          "octave": 4,
          "midi": 66
        },
        "tie": null,
        "accidental": "sharp",
        "source_staff": 0,
        "confidence": 0.75
      },
      {
        "start_beat": 36.0,
        "measure": 11,
        "beat": 3.5,
        "duration_beats": 0.5,
        "pitch": {
          "step": "E",
          "alter": 0,
          "octave": 4,
          "midi": 64
        },
        "tie": null,
        "accidental": null,
        "source_staff": 0,
        "confidence": 0.75
      },
      {
        "start_beat": 36.5,
        "measure": 11,
        "beat": 4.0,
        "duration_beats": 0.5,
        "pitch": {
          "step": "D",
          "alter": 0,
          "octave": 4,
          "midi": 62
        },
        "tie": null,
        "accidental": null,
        "source_staff": 0,
        "confidence": 0.75
      },
      {
        "start_beat": 37.0,
        "measure": 11,
        "beat": 4.5,
        "duration_beats": 0.5,
        "pitch": {
          "step": "E",
          "alter": 0,
          "octave": 4,
          "midi": 64
        },
        "tie": null,
        "accidental": null,
        "source_staff": 0,
        "confidence": 0.75
      },
      {
        "start_beat": 37.5,
        "measure": 12,
        "beat": 1.0,
        "duration_beats": 1.0,
        "pitch": {
          "step": "F",
          "alter": 1,
          "octave": 4,
          "midi": 66
        },
        "tie": null,
        "accidental": "sharp",
        "source_staff": 0,
        "confidence": 0.75
      },
      {
        "start_beat": 38.5,
        "measure": 12,
        "beat": 2.0,
        "duration_beats": 1.0,
        "pitch": {
          "step": "F",
          "alter": 1,
          "octave": 4,
          "midi": 66
        },
        "tie": null,
        "accidental": "sharp",
        "source_staff": 0,
        "confidence": 0.75
      },
      {
        "start_beat": 40.0,
        "measure": 12,
        "beat": 3.5,
        "duration_beats": 0.5,
        "pitch": {
          "step": "D",
          "alter": 0,
          "octave": 4,
          "midi": 62
        },
        "tie": null,
        "accidental": null,
        "source_staff": 0,
        "confidence": 0.75
      },
      {
        "start_beat": 40.5,
        "measure": 12,
        "beat": 4.0,
        "duration_beats": 0.5,
        "pitch": {
          "step": "G",
          "alter": 0,
          "octave": 4,
          "midi": 67
        },
        "tie": null,
        "accidental": null,
        "source_staff": 0,
        "confidence": 0.75
      },
      {
        "start_beat": 41.0,
        "measure": 12,
        "beat": 4.5,
        "duration_beats": 0.5,
        "pitch": {
          "step": "A",
          "alter": 0,
          "octave": 4,
          "midi": 69
        },
        "tie": null,
        "accidental": null,
        "source_staff": 0,
        "confidence": 0.75
      },
      {
        "start_beat": 41.5,
        "measure": 13,
        "beat": 1.0,
        "duration_beats": 1.5,
        "pitch": {
          "step": "B",
          "alter": 0,
          "octave": 4,
          "midi": 71
        },
        "tie": null,
        "accidental": null,
        "source_staff": 0,
        "confidence": 0.75
      },
      {
        "start_beat": 43.0,
        "measure": 13,
        "beat": 2.5,
        "duration_beats": 0.5,
        "pitch": {
          "step": "B",
          "alter": 0,
          "octave": 4,
          "midi": 71
        },
        "tie": null,
        "accidental": null,
        "source_staff": 0,
        "confidence": 0.75
      },
      {
        "start_beat": 43.5,
        "measure": 13,
        "beat": 3.0,
        "duration_beats": 0.5,
        "pitch": {
          "step": "A",
          "alter": 1,
          "octave": 4,
          "midi": 70
        },
        "tie": null,
        "accidental": "sharp",
        "source_staff": 0,
        "confidence": 0.75
      },
      {
        "start_beat": 44.0,
        "measure": 13,
        "beat": 3.5,
        "duration_beats": 0.5,
        "pitch": {
          "step": "A",
          "alter": 1,
          "octave": 4,
          "midi": 70
        },
        "tie": null,
        "accidental": "sharp",
        "source_staff": 0,
        "confidence": 0.75
      },
      {
        "start_beat": 44.5,
        "measure": 13,
        "beat": 4.0,
        "duration_beats": 0.5,
        "pitch": {
          "step": "B",
          "alter": 0,
          "octave": 4,
          "midi": 71
        },
        "tie": null,
        "accidental": null,
        "source_staff": 0,
        "confidence": 0.75
      },
      {
        "start_beat": 45.0,
        "measure": 13,
        "beat": 4.5,
        "duration_beats": 0.5,
        "pitch": {
          "step": "C",
          "alter": 1,
          "octave": 5,
          "midi": 73
        },
        "tie": null,
        "accidental": "sharp",
        "source_staff": 0,
        "confidence": 0.75
      },
      {
        "start_beat": 45.5,
        "measure": 14,
        "beat": 1.0,
        "duration_beats": 2.0,
        "pitch": {
          "step": "B",
          "alter": 0,
          "octave": 4,
          "midi": 71
        },
        "tie": null,
        "accidental": null,
        "source_staff": 0,
        "confidence": 0.75
      },
      {
        "start_beat": 48.0,
        "measure": 14,
        "beat": 3.5,
        "duration_beats": 0.5,
        "pitch": {
          "step": "B",
          "alter": 0,
          "octave": 4,
          "midi": 71
        },
        "tie": null,
        "accidental": null,
        "source_staff": 0,
        "confidence": 0.75
      },
      {
        "start_beat": 48.5,
        "measure": 14,
        "beat": 4.0,
        "duration_beats": 0.5,
        "pitch": {
          "step": "A",
          "alter": 1,
          "octave": 4,
          "midi": 70
        },
        "tie": null,
        "accidental": "sharp",
        "source_staff": 0,
        "confidence": 0.75
      },
      {
        "start_beat": 49.0,
        "measure": 14,
        "beat": 4.5,
        "duration_beats": 0.5,
        "pitch": {
          "step": "B",
          "alter": 0,
          "octave": 4,
          "midi": 71
        },
        "tie": null,
        "accidental": null,
        "source_staff": 0,
        "confidence": 0.75
      },
      {
        "start_beat": 49.5,
        "measure": 15,
        "beat": 1.0,
        "duration_beats": 1.5,
        "pitch": {
          "step": "D",
          "alter": 0,
          "octave": 5,
          "midi": 74
        },
        "tie": null,
        "accidental": null,
        "source_staff": 0,
        "confidence": 0.75
      },
      {
        "start_beat": 51.0,
        "measure": 15,
        "beat": 2.5,
        "duration_beats": 0.5,
        "pitch": {
          "step": "D",
          "alter": 0,
          "octave": 5,
          "midi": 74
        },
        "tie": null,
        "accidental": null,
        "source_staff": 0,
        "confidence": 0.75
      },
      {
        "start_beat": 51.5,
        "measure": 15,
        "beat": 3.0,
        "duration_beats": 0.5,
        "pitch": {
          "step": "C",
          "alter": 0,
          "octave": 5,
          "midi": 72
        },
        "tie": null,
        "accidental": null,
        "source_staff": 0,
        "confidence": 0.75
      },
      {
        "start_beat": 52.0,
        "measure": 15,
        "beat": 3.5,
        "duration_beats": 0.5,
        "pitch": {
          "step": "B",
          "alter": -1,
          "octave": 4,
          "midi": 70
        },
        "tie": null,
        "accidental": "flat",
        "source_staff": 0,
        "confidence": 0.75
      },
      {
        "start_beat": 52.5,
        "measure": 15,
        "beat": 4.0,
        "duration_beats": 0.5,
        "pitch": {
          "step": "C",
          "alter": 0,
          "octave": 5,
          "midi": 72
        },
        "tie": null,
        "accidental": null,
        "source_staff": 0,
        "confidence": 0.75
      },
      {
        "start_beat": 53.0,
        "measure": 15,
        "beat": 4.5,
        "duration_beats": 0.5,
        "pitch": {
          "step": "D",
          "alter": 0,
          "octave": 5,
          "midi": 74
        },
        "tie": null,
        "accidental": null,
        "source_staff": 0,
        "confidence": 0.75
      },
      {
        "start_beat": 53.5,
        "measure": 16,
        "beat": 1.0,
        "duration_beats": 1.0,
        "pitch": {
          "step": "D",
          "alter": 0,
          "octave": 5,
          "midi": 74
        },
        "tie": null,
        "accidental": null,
        "source_staff": 0,
        "confidence": 0.75
      },
      {
        "start_beat": 54.5,
        "measure": 16,
        "beat": 2.0,
        "duration_beats": 1.0,
        "pitch": {
          "step": "A",
          "alter": 0,
          "octave": 4,
          "midi": 69
        },
        "tie": null,
        "accidental": null,
        "source_staff": 0,
        "confidence": 0.75
      },
      {
        "start_beat": 56.0,
        "measure": 16,
        "beat": 3.5,
        "duration_beats": 0.5,
        "pitch": {
          "step": "A",
          "alter": 0,
          "octave": 4,
          "midi": 69
        },
        "tie": null,
        "accidental": null,
        "source_staff": 0,
        "confidence": 0.75
      },
      {
        "start_beat": 56.5,
        "measure": 16,
        "beat": 4.0,
        "duration_beats": 0.5,
        "pitch": {
          "step": "G",
          "alter": 0,
          "octave": 4,
          "midi": 67
        },
        "tie": null,
        "accidental": null,
        "source_staff": 0,
        "confidence": 0.75
      },
      {
        "start_beat": 57.0,
        "measure": 16,
        "beat": 4.5,
        "duration_beats": 0.5,
        "pitch": {
          "step": "F",
          "alter": 1,
          "octave": 4,
          "midi": 66
        },
        "tie": null,
        "accidental": "sharp",
        "source_staff": 0,
        "confidence": 0.75
      },
      {
        "start_beat": 57.5,
        "measure": 17,
        "beat": 1.0,
        "duration_beats": 1.5,
        "pitch": {
          "step": "B",
          "alter": 0,
          "octave": 4,
          "midi": 71
        },
        "tie": null,
        "accidental": null,
        "source_staff": 0,
        "confidence": 0.75
      },
      {
        "start_beat": 59.0,
        "measure": 17,
        "beat": 2.5,
        "duration_beats": 0.5,
        "pitch": {
          "step": "D",
          "alter": 0,
          "octave": 5,
          "midi": 74
        },
        "tie": null,
        "accidental": null,
        "source_staff": 0,
        "confidence": 0.75
      },
      {
        "start_beat": 59.5,
        "measure": 17,
        "beat": 3.0,
        "duration_beats": 0.5,
        "pitch": {
          "step": "G",
          "alter": 0,
          "octave": 4,
          "midi": 67
        },
        "tie": null,
        "accidental": null,
        "source_staff": 0,
        "confidence": 0.75
      },
      {
        "start_beat": 60.0,
        "measure": 17,
        "beat": 3.5,
        "duration_beats": 0.5,
        "pitch": {
          "step": "G",
          "alter": 0,
          "octave": 4,
          "midi": 67
        },
        "tie": null,
        "accidental": null,
        "source_staff": 0,
        "confidence": 0.75
      },
      {
        "start_beat": 60.5,
        "measure": 17,
        "beat": 4.0,
        "duration_beats": 0.5,
        "pitch": {
          "step": "F",
          "alter": 1,
          "octave": 4,
          "midi": 66
        },
        "tie": null,
        "accidental": "sharp",
        "source_staff": 0,
        "confidence": 0.75
      },
      {
        "start_beat": 61.0,
        "measure": 17,
        "beat": 4.5,
        "duration_beats": 0.5,
        "pitch": {
          "step": "E",
          "alter": 0,
          "octave": 4,
          "midi": 64
        },
        "tie": null,
        "accidental": null,
        "source_staff": 0,
        "confidence": 0.75
      },
      {
        "start_beat": 61.5,
        "measure": 18,
        "beat": 1.0,
        "duration_beats": 2.0,
        "pitch": {
          "step": "D",
          "alter": 0,
          "octave": 4,
          "midi": 62
        },
        "tie": null,
        "accidental": null,
        "source_staff": 0,
        "confidence": 0.75
      },
      {
        "start_beat": 63.5,
        "measure": 18,
        "beat": 3.0,
        "duration_beats": 0.5,
        "pitch": {
          "step": "D",
          "alter": 0,
          "octave": 4,
          "midi": 62
        },
        "tie": null,
        "accidental": null,
        "source_staff": 0,
        "confidence": 0.75
      }
    ]
  },
  "tablature": {
    "supported": false,
    "reason": "Tablature is not implemented in the MVP."
  }
}
